ludology/__init__.py
ludology/closet.py
ludology/game.py
ludology/hypothesis.py
ludology/lattice.py
ludology/nimber.py
ludology/printing.py
ludology/sums.py
ludology/surreal.py
ludology/thermography.py
ludology/tools.py
ludology/utils.py
ludology-0.1.2.dist-info/LICENSE.txt
ludology-0.1.2.dist-info/WHEEL
ludology-0.1.2.dist-info/METADATA
ludology-0.1.2.dist-info/RECORD
